<?xml version="1.0" encoding="utf-8" ?>
<Defs>

    <ThingDef ParentName="PlantBase">
        <defName>VEE_Plant_Bluebell</defName>
        <label>bluebell</label>
        <description>A garden flower with a violet–blue teint, with strongly recurved petals. Bluebells are very beautiful, and last long.</description>
        <statBases>
            <MaxHitPoints>85</MaxHitPoints>
            <Beauty>16</Beauty>
            <Nutrition>0.05</Nutrition>
        </statBases>
        <graphicData>
            <texPath>Things/Plants/Bluebells</texPath>
            <graphicClass>Graphic_Random</graphicClass>
        </graphicData>
        <altitudeLayer>Item</altitudeLayer>
        <selectable>true</selectable>
        <ingestible />
        <plant>
            <dieIfLeafless>true</dieIfLeafless>
            <harvestTag>Standard</harvestTag>
            <sowWork>950</sowWork>
            <sowTags>
                <li>Ground</li>
                <li>Decorative</li>
            </sowTags>
            <growMinGlow>0.3</growMinGlow>
            <topWindExposure>0.1</topWindExposure>
            <growDays>3</growDays>
            <lifespanDaysPerGrowDays>6</lifespanDaysPerGrowDays>
            <visualSizeRange>0.3~1.05</visualSizeRange>
            <wildOrder>1</wildOrder>
            <purpose>Beauty</purpose>
        </plant>
    </ThingDef>

    <ThingDef ParentName="PlantBase">
        <defName>VEE_Plant_Gardenia</defName>
        <label>gardenia</label>
        <description>A flower with large petals. Gardenias are very beautiful.</description>
        <statBases>
            <MaxHitPoints>85</MaxHitPoints>
            <Beauty>19</Beauty>
            <Nutrition>0.05</Nutrition>
        </statBases>
        <graphicData>
            <texPath>Things/Plants/Gardenia</texPath>
            <graphicClass>Graphic_Random</graphicClass>
        </graphicData>
        <altitudeLayer>Item</altitudeLayer>
        <selectable>true</selectable>
        <ingestible />
        <plant>
            <dieIfLeafless>true</dieIfLeafless>
            <harvestTag>Standard</harvestTag>
            <sowWork>790</sowWork>
            <sowTags>
                <li>Ground</li>
                <li>Decorative</li>
            </sowTags>
            <growMinGlow>0.3</growMinGlow>
            <topWindExposure>0.1</topWindExposure>
            <growDays>1.8</growDays>
            <lifespanDaysPerGrowDays>4</lifespanDaysPerGrowDays>
            <visualSizeRange>0.3~1.05</visualSizeRange>
            <wildOrder>1</wildOrder>
            <purpose>Beauty</purpose>
        </plant>
    </ThingDef>

    <ThingDef ParentName="PlantBase">
        <defName>VEE_Plant_Gentian</defName>
        <label>gentian</label>
        <description>A large cultivated flower with inimitable blue petals. Gentians are very beautiful.</description>
        <statBases>
            <MaxHitPoints>85</MaxHitPoints>
            <Beauty>21</Beauty>
            <Nutrition>0.05</Nutrition>
        </statBases>
        <graphicData>
            <texPath>Things/Plants/Gentians</texPath>
            <graphicClass>Graphic_Random</graphicClass>
        </graphicData>
        <altitudeLayer>Item</altitudeLayer>
        <selectable>true</selectable>
        <ingestible />
        <plant>
            <dieIfLeafless>true</dieIfLeafless>
            <harvestTag>Standard</harvestTag>
            <sowWork>790</sowWork>
            <sowTags>
                <li>Ground</li>
                <li>Decorative</li>
            </sowTags>
            <growMinGlow>0.3</growMinGlow>
            <topWindExposure>0.1</topWindExposure>
            <growDays>2.2</growDays>
            <lifespanDaysPerGrowDays>3</lifespanDaysPerGrowDays>
            <visualSizeRange>0.4~1.05</visualSizeRange>
            <wildOrder>1</wildOrder>
            <purpose>Beauty</purpose>
        </plant>
    </ThingDef>

    <ThingDef ParentName="PlantBase">
        <defName>VEE_Plant_Petunia</defName>
        <label>petunia</label>
        <description>A long lasting flower with purple petals. Petunias are very beautiful.</description>
        <statBases>
            <MaxHitPoints>85</MaxHitPoints>
            <Beauty>18</Beauty>
            <Nutrition>0.05</Nutrition>
        </statBases>
        <graphicData>
            <texPath>Things/Plants/Petunias</texPath>
            <graphicClass>Graphic_Random</graphicClass>
        </graphicData>
        <altitudeLayer>Item</altitudeLayer>
        <selectable>true</selectable>
        <ingestible />
        <plant>
            <dieIfLeafless>true</dieIfLeafless>
            <harvestTag>Standard</harvestTag>
            <sowWork>790</sowWork>
            <sowTags>
                <li>Ground</li>
                <li>Decorative</li>
            </sowTags>
            <growMinGlow>0.3</growMinGlow>
            <topWindExposure>0.1</topWindExposure>
            <growDays>1.8</growDays>
            <lifespanDaysPerGrowDays>4</lifespanDaysPerGrowDays>
            <visualSizeRange>0.3~1.05</visualSizeRange>
            <wildOrder>1</wildOrder>
            <purpose>Beauty</purpose>
        </plant>
    </ThingDef>

</Defs>
